text_extract/__init__.py
text_extract/banned_selectors.txt
text_extract/boilerplate_words.txt
text_extract/extract.py
text_extract/latex_processing.py
text_extract/line_processing.py
text_extract/py.typed
text_extract/tree_processing.py
text_extract/utils.py
text_extract/configs/randomized_all.yaml
text_extract/mmltex/README
text_extract/mmltex/cmarkup.xsl
text_extract/mmltex/entities.xsl
text_extract/mmltex/glayout.xsl
text_extract/mmltex/mmltex.xsl
text_extract/mmltex/scripts.xsl
text_extract/mmltex/tables.xsl
text_extract/mmltex/tokens.xsl
openwebmath_text_extract-0.1.3.dist-info/METADATA
openwebmath_text_extract-0.1.3.dist-info/WHEEL
openwebmath_text_extract-0.1.3.dist-info/top_level.txt
openwebmath_text_extract-0.1.3.dist-info/RECORD
