Metadata-Version: 2.1
Name: openwebmath-text-extract
Version: 0.1.3
Summary: Text Extractor from OpenWebMath
Author-email: Keiran Paster <keirp@cs.toronto.edu>
Maintainer-email: Luca Soldaini <luca@soldaini.net>
License: Apache-2.0
Project-URL: homepage, https://github.com/soldni/OpenWebMath
Requires-Python: >=3.8
Requires-Dist: resiliparse
Requires-Dist: py-asciimath
Requires-Dist: tabulate
Requires-Dist: lxml
Requires-Dist: pyyaml
Requires-Dist: numpy
Requires-Dist: urllib3
Provides-Extra: dev
Requires-Dist: black >=22.6.0 ; extra == 'dev'
Requires-Dist: isort >=5.10.1 ; extra == 'dev'
Requires-Dist: mypy >=0.971 ; extra == 'dev'
Requires-Dist: pytest >=5.2 ; extra == 'dev'
Requires-Dist: ipython >=8.4.0 ; extra == 'dev'
Requires-Dist: autopep8 >=1.7.0 ; extra == 'dev'
Requires-Dist: flake8 >=5.0 ; extra == 'dev'
Requires-Dist: ipdb >=0.13.0 ; extra == 'dev'
Requires-Dist: flake8-pyi >=22.8.1 ; extra == 'dev'
Requires-Dist: Flake8-pyproject >=1.1.0 ; extra == 'dev'
